torchvtk/__init__.py
torchvtk/benchmarks/__init__.py
torchvtk/benchmarks/benchmark_cq500_hdf5.py
torchvtk/benchmarks/benchmark_cq500_torch.py
torchvtk/benchmarks/benchmark_dataset.py
torchvtk/benchmarks/benchmark_medical_decathlon.py
torchvtk/converters/__init__.py
torchvtk/converters/torch_to_hdf5.py
torchvtk/converters/dicom/__init__.py
torchvtk/converters/dicom/cq500.py
torchvtk/converters/dicom/utils.py
torchvtk/converters/hdf5/__init__.py
torchvtk/converters/hdf5/hdf5_creation_numpy.py
torchvtk/converters/hdf5/hdf5_creation_pytorch_dataset.py
torchvtk/converters/hdf5/nfiti_crawler.py
torchvtk/data/cq500ct0.pt
torchvtk/datasets/__init__.py
torchvtk/datasets/download.py
torchvtk/datasets/hdf5_dataset.py
torchvtk/datasets/npy_dataset.py
torchvtk/datasets/queue.py
torchvtk/datasets/torch_dataset.py
torchvtk/datasets/urls.py
torchvtk/rendering/__init__.py
torchvtk/rendering/raycast.py
torchvtk/rendering/tf_viewer.py
torchvtk/transforms/__init__.py
torchvtk/transforms/dict_transform.py
torchvtk/utils/__init__.py
torchvtk/utils/common.py
torchvtk/utils/mp.py
torchvtk/utils/tf_generate.py
torchvtk/utils/tf_utils.py
torchvtk/utils/volume_utils.py
torchvtk-0.4.9.dist-info/LICENSE
torchvtk-0.4.9.dist-info/METADATA
torchvtk-0.4.9.dist-info/WHEEL
torchvtk-0.4.9.dist-info/dependency_links.txt
torchvtk-0.4.9.dist-info/top_level.txt
torchvtk-0.4.9.dist-info/RECORD
