Metadata-Version: 2.1
Name: torchvtk
Version: 0.4.9
Summary: Efficient data loading and visualization for volumes in PyTorch
Home-page: https://github.com/torchvtk/torchvtk
Author: Dominik Engel, Marc Fabian Mezger
License: MIT
Platform: UNKNOWN
License-File: LICENSE
Requires-Dist: torch (>=1.6)
Requires-Dist: torchvision
Requires-Dist: numpy
Requires-Dist: matplotlib
Requires-Dist: psutil
Requires-Dist: tqdm
